sumoslack/__init__.py
sumoslack/api.py
sumoslack/main.py
sumoslack/slackcollector.yaml
sumologic_slack-1.1.2.dist-info/LICENSE
sumologic_slack-1.1.2.dist-info/METADATA
sumologic_slack-1.1.2.dist-info/WHEEL
sumologic_slack-1.1.2.dist-info/entry_points.txt
sumologic_slack-1.1.2.dist-info/top_level.txt
sumologic_slack-1.1.2.dist-info/zip-safe
sumologic_slack-1.1.2.dist-info/RECORD
