Metadata-Version: 2.1
Name: sumologic-slack
Version: 1.1.2
Summary: Sumo Logic collection solution for slack
Home-page: https://github.com/SumoLogic/sumologic-slack
Author: SumoLogic
Author-email: it@sumologic.com, apps-team@sumologic.com
License: PSF
Keywords: sumologic python rest api log management analytics logreduce slack agent security siem collector forwarder
Platform: UNKNOWN
Classifier: Development Status :: 4 - Beta
Classifier: Intended Audience :: Developers
Classifier: Programming Language :: Python :: 2.7
Classifier: Programming Language :: Python :: 3.7
Classifier: Operating System :: OS Independent
Requires-Dist: slackclient (==2.0.0)
Requires-Dist: websocket-client (==0.56.0)
Requires-Dist: sumologic-appclient-sdk (==2.0.2)
